xbitdiff/__init__.py
xbitdiff/_version.py
xbitdiff/accessor.py
xbitdiff-0.2.dist-info/LICENSE
xbitdiff-0.2.dist-info/METADATA
xbitdiff-0.2.dist-info/WHEEL
xbitdiff-0.2.dist-info/top_level.txt
xbitdiff-0.2.dist-info/RECORD
