Metadata-Version: 2.1
Name: xbitdiff
Version: 0.2
Summary: A simple xarray extension for differential compression
Maintainer-email: Timothy Hodson <thodson@usgs.gov>
Project-URL: homepage, https://github.com/thodson-usgs/xbitdiff
Keywords: xarray,bitwise diff
Classifier: Programming Language :: Python :: 3
Requires-Python: >=3.8
License-File: LICENSE
Requires-Dist: xarray
Provides-Extra: test
Requires-Dist: pytest >5.0.0 ; extra == 'test'
Requires-Dist: pytest-cov[all] ; extra == 'test'
